gamebench_api_client/__init__.py
gamebench_api_client/global_settings.py
gamebench_api_client/singleton.py
gamebench_api_client/api/__init__.py
gamebench_api_client/api/requests_retriever/__init__.py
gamebench_api_client/api/requests_retriever/builder/__init__.py
gamebench_api_client/api/requests_retriever/builder/request_builder.py
gamebench_api_client/api/requests_retriever/builder/request_director.py
gamebench_api_client/api/requests_retriever/builder/attributes/__init__.py
gamebench_api_client/api/requests_retriever/builder/attributes/attributes_creator.py
gamebench_api_client/api/requests_retriever/builder/method/__init__.py
gamebench_api_client/api/requests_retriever/builder/method/method_creator.py
gamebench_api_client/api/requests_retriever/builder/url/__init__.py
gamebench_api_client/api/requests_retriever/builder/url/url_builder.py
gamebench_api_client/api/requests_retriever/builder/url/url_director.py
gamebench_api_client/api/requests_retriever/request_adapter/__init__.py
gamebench_api_client/api/requests_retriever/request_adapter/adapter.py
gamebench_api_client/api/response/__init__.py
gamebench_api_client/api/response/response_mediator.py
gamebench_api_client/api/response/response_retriever.py
gamebench_api_client/api/utilities/__init__.py
gamebench_api_client/api/utilities/dataframe_utilities.py
gamebench_api_client/models/__init__.py
gamebench_api_client/models/abstract_model.py
gamebench_api_client/models/authentication/__init__.py
gamebench_api_client/models/authentication/authentication.py
gamebench_api_client/models/creator/__init__.py
gamebench_api_client/models/creator/model_creator.py
gamebench_api_client/models/dataframes/__init__.py
gamebench_api_client/models/dataframes/generic/__init__.py
gamebench_api_client/models/dataframes/generic/abstract_generic.py
gamebench_api_client/models/dataframes/generic/generic_models.py
gamebench_api_client/models/dataframes/time_series/__init__.py
GameBenchAPI_PyClient_BigFish-1.0.3.dist-info/LICENSE.txt
GameBenchAPI_PyClient_BigFish-1.0.3.dist-info/METADATA
GameBenchAPI_PyClient_BigFish-1.0.3.dist-info/WHEEL
GameBenchAPI_PyClient_BigFish-1.0.3.dist-info/top_level.txt
GameBenchAPI_PyClient_BigFish-1.0.3.dist-info/RECORD
