Metadata-Version: 2.1
Name: GameBenchAPI-PyClient-BigFish
Version: 1.0.3
Summary: A GameBench API Client Library.
Home-page: https://github.com/bigfishgames/GameBenchAPI-PyClient
Author: Big Fish Games, Inc.
Author-email: 
License: UNKNOWN
Platform: UNKNOWN
Classifier: Programming Language :: Python :: 3.7
Classifier: License :: OSI Approved :: BSD License
Classifier: Operating System :: OS Independent
Requires-Python: >=3.7
Requires-Dist: pandas (~=0.24.2)
Requires-Dist: urllib3 (<1.25,>=1.24.2)
Requires-Dist: requests (~=2.21.0)
